zsynctech_maestro_sdk/__init__.py
zsynctech_maestro_sdk/errors/__init__.py
zsynctech_maestro_sdk/errors/__pycache__/__init__.cpython-313.pyc
zsynctech_maestro_sdk/errors/__pycache__/exceptions.cpython-313.pyc
zsynctech_maestro_sdk/errors/exceptions.py
zsynctech_maestro_sdk/interfaces/__init__.py
zsynctech_maestro_sdk/interfaces/__pycache__/__init__.cpython-313.pyc
zsynctech_maestro_sdk/interfaces/__pycache__/broker.cpython-313.pyc
zsynctech_maestro_sdk/interfaces/broker.py
zsynctech_maestro_sdk/maestro.py
zsynctech_maestro_sdk/messaging/__init__.py
zsynctech_maestro_sdk/messaging/__pycache__/__init__.cpython-313.pyc
zsynctech_maestro_sdk/messaging/__pycache__/rabbitmq.cpython-313.pyc
zsynctech_maestro_sdk/messaging/rabbitmq.py
zsynctech_maestro_sdk/models/__pycache__/execution.cpython-313.pyc
zsynctech_maestro_sdk/models/__pycache__/step.cpython-313.pyc
zsynctech_maestro_sdk/models/__pycache__/task.cpython-313.pyc
zsynctech_maestro_sdk/models/execution.py
zsynctech_maestro_sdk/models/step.py
zsynctech_maestro_sdk/models/task.py
zsynctech_maestro_sdk/utils.py
zsynctech_maestro_sdk-0.1.2.dist-info/METADATA
zsynctech_maestro_sdk-0.1.2.dist-info/WHEEL
zsynctech_maestro_sdk-0.1.2.dist-info/RECORD
