Metadata-Version: 2.3
Name: zsynctech-maestro-sdk
Version: 0.1.2
Summary: 
Author: rodrigozavan
Author-email: rodrigozavan104@gmail.com
Requires-Python: >=3.13
Classifier: Programming Language :: Python :: 3
Classifier: Programming Language :: Python :: 3.13
Requires-Dist: mkdocs-material (>=9.6.14,<10.0.0)
Requires-Dist: pika (>=1.3.2,<2.0.0)
Requires-Dist: pydantic (>=2.11.4,<3.0.0)
Requires-Dist: retry (>=0.9.2,<0.10.0)
Requires-Dist: uuid7 (>=0.1.0,<0.2.0)
